[
      {
         "source": {
            "id": "bbc-news",
            "name": "BBC News"
         },
         "author": "https://www.facebook.com/bbcnews",
         "title": "Oxford-AstraZeneca: Denmark suspends vaccine 'as a precaution'",
         "description": "The decision follows a death and reports of blood clots, but the health minister says no link is established.",
         "url": "https://www.bbc.co.uk/news/world-europe-56357760",
         "urlToImage": "https://ichef.bbci.co.uk/news/1024/branded_news/15DEE/production/_117528598_den.jpg",
         "publishedAt": "2021-03-11T11:32:43Z",
         "content": "image captionDenmark's health authority says the hold on the rollout of the Oxford-AstraZeneca vaccine is temporary\r\nDenmark has temporarily halted use of the Oxford-AstraZeneca vaccine as a precauti\u2026 [+3146 chars]"
      },
      {
         "source": {
            "id": "bbc-news",
            "name": "BBC News"
         },
         "author": "https://www.facebook.com/bbcnews",
         "title": "The Hebrides' wild swimming 'real-life' mermaid",
         "description": "Kate Macleod can be found swimming in seas and lochs around the Western Isles in summer - and winter.",
         "url": "https://www.bbc.co.uk/news/uk-scotland-highlands-islands-56359621",
         "urlToImage": "https://ichef.bbci.co.uk/news/1024/branded_news/141D8/production/_117529328_mermaideight.jpg",
         "publishedAt": "2021-03-11T11:46:30Z",
         "content": "A wild swimmer has been exploring the Western Isles' coast in a custom-made mermaid tale.\r\nimage copyrightBBC Alba/MacTV\r\nimage captionKate MacLeod swimming using one of her custom-made mermaid tales\u2026 [+1743 chars]"
      },
      {
         "source": {
            "id": "bbc-news",
            "name": "BBC News"
         },
         "author": "https://www.facebook.com/bbcnews",
         "title": "Teen Vogue editor Alexi McCammond apologises for 'anti-Asian' tweets",
         "description": "Staff at the magazine had said editor Alexi McCammond's tweets threatened the outlet's values.",
         "url": "https://www.bbc.co.uk/news/world-us-canada-56359165",
         "urlToImage": "https://ichef.bbci.co.uk/news/1024/branded_news/10E98/production/_117527296_gettyimages-1183816965.jpg",
         "publishedAt": "2021-03-11T12:30:02Z",
         "content": "image copyrightGetty Images\r\nimage captionAlexi McCammond, 29, was hired by Teen Vogue last week\r\nThe newly-appointed editor of Teen Vogue has apologised for \"racist and homophobic\" tweets she wrote \u2026 [+2859 chars]"
      },
      {
         "source": {
            "id": "bbc-news",
            "name": "BBC News"
         },
         "author": "https://www.facebook.com/bbcnews",
         "title": "Roblox: David Baszucki worth $4.6bn as shares soar",
         "description": "First day's trading sees David Baszucki's firm now worth more than some of the biggest gaming firms.",
         "url": "https://www.bbc.co.uk/news/technology-56359211",
         "urlToImage": "https://ichef.bbci.co.uk/news/1024/branded_news/E4D6/production/_117528585_davidbaszucki.jpg",
         "publishedAt": "2021-03-11T12:44:45Z",
         "content": "image copyrightGetty Images\r\nimage captionDavid Baszucki will be celebrating after his stake in Roblox soared in value\r\nChief executive of Roblox David Baszucki may well be letting out the \"Oof\" soun\u2026 [+2762 chars]"
      },
      {
         "source": {
            "id": "bbc-news",
            "name": "BBC News"
         },
         "author": null,
         "title": "2021/03/11 12:00 GMT",
         "description": "The latest five minute news bulletin from BBC World Service.",
         "url": "https://www.bbc.co.uk/programmes/w172x5pc0dlv8sw",
         "urlToImage": "https://ichef.bbci.co.uk/images/ic/1200x675/p060dh18.jpg",
         "publishedAt": "2021-03-11T12:06:00Z",
         "content": "The latest five minute news bulletin from BBC World Service."
      },
      {
         "source": {
            "id": "bbc-news",
            "name": "BBC News"
         },
         "author": "https://www.facebook.com/bbcnews",
         "title": "Circle of Hope: Boarding school couple charged after TikTok abuse allegations",
         "description": "The ex-owners of Circle of Hope Girls' Ranch face more than 100 charges after women speak out online.",
         "url": "https://www.bbc.co.uk/news/world-us-canada-56357828",
         "urlToImage": "https://ichef.bbci.co.uk/news/1024/branded_news/B2FF/production/_117532854_collage.jpg",
         "publishedAt": "2021-03-11T14:54:58Z",
         "content": "image captionThe couple's estranged daughter has helped expose their alleged abuse of girls at their ranch\r\nThe owners of a shuttered religious boarding school in Missouri, USA, are facing dozens of \u2026 [+4660 chars]"
      },
      {
         "source": {
            "id": "bbc-news",
            "name": "BBC News"
         },
         "author": "https://www.facebook.com/bbcnews",
         "title": "Sven Badzak death: Man, 20, charged with murder",
         "description": "Aspiring lawyer Sven Badzak was chased and then attacked while he was out to buy food.",
         "url": "https://www.bbc.co.uk/news/uk-england-london-56361293",
         "urlToImage": "https://ichef.bbci.co.uk/news/1024/branded_news/D347/production/_116878045_ffca2ac0-bbaa-45b6-91f9-38ceeab2fb62.jpg",
         "publishedAt": "2021-03-11T11:53:45Z",
         "content": "image copyrightMetropolitan Police\r\nimage captionSven Badzak has been described by his mother as someone \"who would never raise a hand unless he was going to lift you up\"\r\nA man has been charged with\u2026 [+840 chars]"
      },
      {
         "source": {
            "id": "bbc-news",
            "name": "BBC News"
         },
         "author": "https://www.facebook.com/bbcnews",
         "title": "Rushanara Ali: 'End of distressing period' for MP after 'stream of abuse'",
         "description": "Labour's Rushanara Ali said she \"lived in fear\" during an 18-month barrage of abusive messages.",
         "url": "https://www.bbc.co.uk/news/uk-england-london-56361297",
         "urlToImage": "https://ichef.bbci.co.uk/news/1024/branded_news/050C/production/_117529210_hi040857655.jpg",
         "publishedAt": "2021-03-11T13:09:40Z",
         "content": "image copyright UK Parliament\r\nimage captionHussain Sha said he would \"blow up Rushanara's office terrorist-style with petrol\"\r\nA Labour MP exposed to a stream of harassment by a constituent is marki\u2026 [+1918 chars]"
      },
      {
         "source": {
            "id": "bbc-news",
            "name": "BBC News"
         },
         "author": null,
         "title": "Miguel Cummins: Kent sign West Indies bowler for start of season",
         "description": "Kent sign West Indies fast bowler Miguel Cummins for the first eight matches of the County Championship campaign.",
         "url": "https://www.bbc.co.uk/sport/cricket/56362792",
         "urlToImage": "https://ichef.bbci.co.uk/live-experience/cps/624/cpsprodpb/0783/production/_117532910_miguelcummins.jpg",
         "publishedAt": "2021-03-11T13:54:46Z",
         "content": "Miguel Cummins took first-innings figures of 5-62 for Middlesex when the north London club drew with Kent in the Bob Willis Trophy last August\r\nKent have signed West Indies fast bowler Miguel Cummins\u2026 [+476 chars]"
      },
      {
         "source": {
            "id": "bbc-news",
            "name": "BBC News"
         },
         "author": null,
         "title": "India v England: Eoin Morgan says tourists are not prioritising T20",
         "description": "Captain Eoin Morgan says it is a \"rarity\" for England to be at full strength in their Twenty20 series against India.",
         "url": "https://www.bbc.co.uk/sport/cricket/56363459",
         "urlToImage": "https://ichef.bbci.co.uk/live-experience/cps/624/cpsprodpb/14E27/production/_117534558_eoinmorgan.jpg",
         "publishedAt": "2021-03-11T14:16:26Z",
         "content": "England captain Eoin Morgan is set to play his 100th T20 international during the series against India\r\nCaptain Eoin Morgan says it is a \"rarity\" for England to be at full strength in their Twenty20 \u2026 [+2910 chars]"
      },
      {
         "source": {
            "id": "bbc-news",
            "name": "BBC News"
         },
         "author": null,
         "title": "2021/03/11 14:00 GMT",
         "description": "The latest five minute news bulletin from BBC World Service.",
         "url": "https://www.bbc.co.uk/programmes/w172x5pc0dlvj94",
         "urlToImage": "https://ichef.bbci.co.uk/images/ic/1200x675/p060dh18.jpg",
         "publishedAt": "2021-03-11T14:06:00Z",
         "content": "The latest five minute news bulletin from BBC World Service."
      },
      {
         "source": {
            "id": "bbc-news",
            "name": "BBC News"
         },
         "author": null,
         "title": "Pro14: Glasgow v Ospreys (Fri)",
         "description": "Team news and preview for Ospreys' Friday night visit to Glasgow in Pro14.",
         "url": "https://www.bbc.co.uk/sport/rugby-union/56357903",
         "urlToImage": "https://ichef.bbci.co.uk/live-experience/cps/624/cpsprodpb/585F/production/_117532622_cdf_240121_connacht_v_ospreys_50.jpg",
         "publishedAt": "2021-03-11T12:19:46Z",
         "content": "Reuben Morgan Williams scores Ospreys' opening try in October's 23-15 Pro14 victory over Glasgow at Liberty Stadium\r\n<table><tr><th>Pro14: Glasgow Warriors v Ospreys</th></tr>\r\n<tr><td>Venue: Scotsto\u2026 [+3125 chars]"
      },
      {
         "source": {
            "id": "bbc-news",
            "name": "BBC News"
         },
         "author": "https://www.facebook.com/bbcnews",
         "title": "Rhondda: Wenjing Lin's murder accused appears in court",
         "description": "Wenjing Lin died on Friday at her family's takeaway restaurant.",
         "url": "https://www.bbc.co.uk/news/uk-wales-56358022",
         "urlToImage": "https://ichef.bbci.co.uk/news/1024/branded_news/373F/production/_117534141_defendantde15.jpg",
         "publishedAt": "2021-03-11T13:43:45Z",
         "content": "image captionDefendant Chun Xu appeared at Merthyr Tydfil Magistrates' Court on Thursday\r\nA man has appeared in court charged with the murder of a 16-year-old girl and the attempted murder of a man, \u2026 [+587 chars]"
      },
      {
         "source": {
            "id": "bbc-news",
            "name": "BBC News"
         },
         "author": "https://www.facebook.com/bbcnews",
         "title": "Academy Museum Why this could be a mecca for movie fans",
         "description": "After decades of wrangling this ambitious venue devoted to cinema is finally set to open.",
         "url": "https://www.bbc.co.uk/news/entertainment-arts-56358266",
         "urlToImage": "https://ichef.bbci.co.uk/news/1024/branded_news/73E8/production/_117527692_exteriorcapture.jpg",
         "publishedAt": "2021-03-11T15:42:35Z",
         "content": "By Vincent DowdArts correspondent, BBC News\r\nimage copyrightAcademy Museum Foundation\r\nimage captionThe original five-storey 1939 site now includes a new spherical building designed by Italian archit\u2026 [+5703 chars]"
      },
      {
         "source": {
            "id": "bbc-news",
            "name": "BBC News"
         },
         "author": "https://www.facebook.com/bbcnews",
         "title": "Woman sentenced over neglect of 'caged' toddler",
         "description": "Claire Boyle, 34, was ordered to carry out community service after being convicted on neglect charges.",
         "url": "https://www.bbc.co.uk/news/uk-scotland-56360211",
         "urlToImage": "https://ichef.bbci.co.uk/news/1024/branded_news/F251/production/_117533026_cagearrivals.1_frame_2138.jpg",
         "publishedAt": "2021-03-11T13:03:17Z",
         "content": "image captionTimothy Johnstone and Claire Boyle arriving at Kilmarnock Sheriff Court\r\nA woman who kept a two-year-old child in a makeshift cage has been ordered to carry out community service.\r\nClair\u2026 [+1874 chars]"
      },
      {
         "source": {
            "id": "bbc-news",
            "name": "BBC News"
         },
         "author": null,
         "title": "South Africa cricket captain Temba Bavuma inspired by England's Eoin Morgan",
         "description": "South Africa's limited-overs cricket captain Temba Bavuma admits he looks to his England counterpart Eoin Morgan for inspiration.",
         "url": "https://www.bbc.co.uk/sport/africa/56344990",
         "urlToImage": "https://ichef.bbci.co.uk/live-experience/cps/624/cpsprodpb/C524/production/_117386405_bavuma_getty2.jpg",
         "publishedAt": "2021-03-11T11:12:46Z",
         "content": "South Africa's Temba Bavuma in action\r\nNot only is Temba Bavuma the first permanent black African captain of a South African international cricket team but he has three World Cups to prepare for.\r\nAs\u2026 [+3417 chars]"
      },
      {
         "source": {
            "id": "bbc-news",
            "name": "BBC News"
         },
         "author": "https://www.facebook.com/bbcnews",
         "title": "Covid vaccine: How many people has India vaccinated?",
         "description": "More than 20 million people in India have received at least one dose of a coronavirus vaccine so far.",
         "url": "https://www.bbc.co.uk/news/world-asia-india-56345591",
         "urlToImage": "https://ichef.bbci.co.uk/news/1024/branded_news/C6FE/production/_117524905_gettyimages-1231631749.jpg",
         "publishedAt": "2021-03-11T05:08:09Z",
         "content": "More than 20 million people in India have received at least one dose of a coronavirus vaccine in what is the world's biggest inoculation drive.\r\nSince the pandemic began, India has confirmed more tha\u2026 [+3874 chars]"
      },
      {
         "source": {
            "id": "bbc-news",
            "name": "BBC News"
         },
         "author": null,
         "title": "Covid: The man with \"super antibodies\"",
         "description": "John Hollis has antibodies that can kill the virus and variants but the discovery was nearly missed.",
         "url": "https://www.bbc.co.uk/news/av/world-us-canada-56324050",
         "urlToImage": "https://ichef.bbci.co.uk/images/ic/400xn/p099b25p.jpg",
         "publishedAt": "2021-03-11T00:01:41Z",
         "content": "John Hollis didnt realise hed been infected with Covid-19. But he later discovered hes one of the rare people who has super antibodies. \r\nThe antibodies are so good at killing the virus, hes practica\u2026 [+216 chars]"
      },
      {
         "source": {
            "id": "bbc-news",
            "name": "BBC News"
         },
         "author": "https://www.facebook.com/bbcnews",
         "title": "Covid: Texas and Mississippi lifting restrictions too soon?",
         "description": "Two US states are lifting compulsory coronavirus restrictions, but are they in a position to do so?",
         "url": "https://www.bbc.co.uk/news/world-us-canada-56297329",
         "urlToImage": "https://ichef.bbci.co.uk/news/1024/branded_news/7FF8/production/_117506723_austin_mask_gettyimages-1231493646.jpg",
         "publishedAt": "2021-03-11T00:44:08Z",
         "content": "By Jake HortonBBC Reality Check\r\nimage captionTexas is some way off reaching wider immunity through vaccinations\r\nThe governors of the US states of Texas and Mississippi have lifted all compulsory Co\u2026 [+5192 chars]"
      },
      {
         "source": {
            "id": "bbc-news",
            "name": "BBC News"
         },
         "author": null,
         "title": "Palin and Jones: 'We didn't talk about the stammer'",
         "description": "Former rugby player Mark Jones and Sir Michael Palin talk about their experiences of stammering.",
         "url": "https://www.bbc.co.uk/news/av/uk-56351958",
         "urlToImage": "https://ichef.bbci.co.uk/images/ic/400xn/p099955p.jpg",
         "publishedAt": "2021-03-11T00:59:57Z",
         "content": "Around one and a half million adults in the UK have a stammer. For some - it is obvious when they speak. For many others, it's something they manage to hide - sometimes from even those closest to the\u2026 [+285 chars]"
      },{
         "source": {
            "id": "business-insider",
            "name": "Business Insider"
         },
         "author": "Grace Dean",
         "title": "Thailand follows Denmark in suspending AstraZeneca's COVID-19 vaccine, pending an investigation into possible side effects",
         "description": "Summary List PlacementThailand said Friday it had paused use of AstraZeneca's COVID-19 vaccine while investigators looked into potential side effects and adverse reactions, becoming the first Asian country to make the move.\nDenmark, Norway, and Iceland all sa\u2026",
         "url": "https://www.businessinsider.com/thailand-suspends-astrazeneca-covid-vaccine-side-effects-blood-clots-denmark-2021-3",
         "urlToImage": "https://i.insider.com/604b3433b1973700196949b5?width=1200&format=jpeg",
         "publishedAt": "2021-03-12T09:39:35Z",
         "content": "Thailand said Friday it had paused use of AstraZeneca's COVID-19 vaccine while investigators looked into potential side effects and adverse reactions, becoming the first Asian country to make the mov\u2026 [+2998 chars]"
      },
      {
         "source": {
            "id": "business-insider",
            "name": "Business Insider"
         },
         "author": "ddefrancesco@businessinsider.com (Dan DeFrancesco,Jordan Parker Erb)",
         "title": "Vista fundraising - American Airlines' $10 bln debt binge - Fintech M&A on the rise",
         "description": "The top finance stories for March 12, including the latest news on Vista Equity Partners continuing to fundraise.",
         "url": "https://www.businessinsider.com/top-finance-stories-of-the-day-for-march-12-2021-3",
         "urlToImage": "https://i.insider.com/6042bc3f44d8e300117b96af?width=1200&format=jpeg",
         "publishedAt": "2021-03-12T10:50:00Z",
         "content": "Good morning and welcome to Insider Finance. I'm Dan DeFrancesco, and here's what's on the agenda today:\r\nWe are also looking for nominations for upcoming list of top equity research analysts under 3\u2026 [+2782 chars]"
      },
      {
         "source": {
            "id": "business-insider",
            "name": "Business Insider"
         },
         "author": "kduffy@insider.com (Kate Duffy)",
         "title": "Ghislaine Maxwell is selling her London home to raise funds for her legal defense in the Epstein case",
         "description": "Ghislaine Maxwell, the alleged madam of convicted sex trafficker Jeffrey Epstein, is selling her home in upmarket Belgravia, the WSJ reported.",
         "url": "https://www.businessinsider.com/ghislaine-maxwell-sells-london-house-fund-legal-defense-jeffrey-epstein-2021-3",
         "urlToImage": "https://i.insider.com/604b34bdb1973700196949b6?width=1200&format=jpeg",
         "publishedAt": "2021-03-12T10:46:39Z",
         "content": "Ghislaine Maxwell, the alleged madam of the convicted sex trafficker Jeffrey Epstein, is selling her London home to raise funds for her legal defense, The Wall Street Journal reported on Thursday, ci\u2026 [+2033 chars]"
      },
      {
         "source": {
            "id": "business-insider",
            "name": "Business Insider"
         },
         "author": "Aleeya Mayo",
         "title": "Hollywood is losing out on $10 billion in revenue every year by underfunding work by Black creators",
         "description": "Summary List PlacementA recent study conducted by the consulting firm McKinsey found that Hollywood could see a boost in annual revenue by $10 billion, bringing revenues to more than $150 billion every year, if the industry addresses the racial inequalities t\u2026",
         "url": "https://www.businessinsider.com/hollywood-could-boost-revenue-by-10-billion-2021-3",
         "urlToImage": "https://i.insider.com/604bad3a10c8760018b92f8b?width=1200&format=jpeg",
         "publishedAt": "2021-03-12T20:36:29Z",
         "content": "A recent study conducted by the consulting firm McKinsey found that Hollywood could see a boost in annual revenue by $10 billion, bringing revenues to more than $150 billion every year, if the indust\u2026 [+3314 chars]"
      },
      {
         "source": {
            "id": "business-insider",
            "name": "Business Insider"
         },
         "author": "Michael Goodman",
         "title": "16 people who made news this week in the startup and venture world, from Snoop Dogg to Mary Meeker",
         "description": "Summary List PlacementHello and welcome to the debut of Venture Week, Insider's weekly wrap of people from the startup and venture capital universe who made news.\nThe entries below aren't all necessarily the biggest news items of the week \u2014 we assume you've s\u2026",
         "url": "https://www.businessinsider.com/ventureweek-16-people-startup-vc-news-jayz-snoop-reid-hoffman-2021-3",
         "urlToImage": "https://i.insider.com/6047fcf8df53f8001802a606?width=1200&format=jpeg",
         "publishedAt": "2021-03-12T20:18:11Z",
         "content": "Hello and welcome to the debut of Venture Week, Insider's weekly wrap of people from the startup and venture capital universe who made news.\r\nThe entries below aren't all necessarily the biggest news\u2026 [+6579 chars]"
      },
      {
         "source": {
            "id": "business-insider",
            "name": "Business Insider"
         },
         "author": "Madison Hall",
         "title": "The DOJ expects to charge 100 more people in the Capitol insurrection and they've received 210,000 tips helping identify rioters",
         "description": "Summary List PlacementThe US Department of Justice expects to charge 100 more people believed to be involved in the January 6 Capitol breach after receiving 210,000 tips identifying rioters, a new court filing shows.\nA little over two months after the attack \u2026",
         "url": "https://www.businessinsider.com/doj-received-210000-tips-will-charge-100-more-capitol-insurrection-2021-3",
         "urlToImage": "https://i.insider.com/601bc195ee136f00183aa3a1?width=1200&format=jpeg",
         "publishedAt": "2021-03-12T18:18:29Z",
         "content": "The US Department of Justice expects to charge 100 more people believed to be involved in the January 6 Capitol breach after receiving 210,000 tips identifying rioters, a new court filing shows.\r\nA l\u2026 [+2269 chars]"
      },
      {
         "source": {
            "id": "business-insider",
            "name": "Business Insider"
         },
         "author": "Camila DeChalus and Kimberly Leonard",
         "title": "Is it a crime to give away leftover COVID shots? Doctors and other healthcare workers fear legal consequences as they wait for Justice Department guidance.",
         "description": "Summary List PlacementDoctors and other healthcare workers are finding themselves straddling a confusing line between making sure no COVID vaccine goes to waste, and committing potential crimes if they give away unclaimed shots.\u00a0\nWhen people don't show up for\u2026",
         "url": "https://www.businessinsider.com/is-it-crime-to-give-away-unclaimed-covid-shots-doctors-dilema-2021-3",
         "urlToImage": "https://i.insider.com/604bc5bd10c8760018b9300d?width=1200&format=jpeg",
         "publishedAt": "2021-03-12T21:15:49Z",
         "content": "Doctors and other healthcare workers are finding themselves straddling a confusing line between making sure no COVID vaccine goes to waste, and committing potential crimes if they give away unclaimed\u2026 [+9668 chars]"
      },
      {
         "source": {
            "id": "business-insider",
            "name": "Business Insider"
         },
         "author": "Ben Gilbert",
         "title": "Former Theranos CEO Elizabeth Holmes is pregnant, and is requesting her federal trial be delayed again",
         "description": "Summary List PlacementFounder and former Theranos CEO Elizabeth Holmes is pregnant, according to new court documents.\nHolmes expects to give birth in July, and is requesting a delay to her federal trial, according to newly filed court documents. Both Holmes' \u2026",
         "url": "https://www.businessinsider.com/theranos-elizabeth-holmes-pregnant-trial-delay-request-2021-3",
         "urlToImage": "https://i.insider.com/604bd08410c8760018b93051?width=1200&format=jpeg",
         "publishedAt": "2021-03-12T21:02:20Z",
         "content": "Founder and former Theranos CEO Elizabeth Holmes is pregnant, according to new court documents.\r\nHolmes expects to give birth in July, and is requesting a delay to her federal trial, according to new\u2026 [+1257 chars]"
      },
      {
         "source": {
            "id": "business-insider",
            "name": "Business Insider"
         },
         "author": "insider@insider.com (Melanie Weir)",
         "title": "How to get HBO Max on an Amazon Fire Stick and watch shows like 'Game of Thrones' or 'Friends'",
         "description": "You can get HBO Max on an Amazon Fire Stick, and all other Amazon devices, simply by downloading the app and logging in.",
         "url": "https://www.businessinsider.com/how-to-get-hbo-max-on-amazon-fire-stick",
         "urlToImage": "https://i.insider.com/604bd27e10c8760018b93066?width=1200&format=jpeg",
         "publishedAt": "2021-03-12T23:27:43Z",
         "content": "HBO's streaming service HBO Max has tons of hit series people love, like \"Friends,\" \"Rick and Morty,\" and \"The Bachelor,\" plus great originals like \"Euphoria,\" \"Game of Thrones,\" and \"Last Week Tonig\u2026 [+1129 chars]"
      },
      {
         "source": {
            "id": "business-insider",
            "name": "Business Insider"
         },
         "author": "Charles Davis",
         "title": "New York Senators Chuck Schumer and Kirsten Gillibrand say Gov. Andrew Cuomo 'should resign'",
         "description": "Summary List PlacementNew York's two Democratic US senators said Friday that Gov. Andrew Cuomo should step down amid allegations from six women that he engaged in sexual harassment.\nIn a joint statement, Senate Majority Leader Chuck Schumer and Sen. Kirsten G\u2026",
         "url": "https://www.businessinsider.com/new-york-senators-schumer-gillibrand-say-cuomo-should-resign-2021-3",
         "urlToImage": "https://i.insider.com/604bf0b6fea127001886a9a8?width=1200&format=jpeg",
         "publishedAt": "2021-03-12T23:04:00Z",
         "content": "New York's two Democratic US senators said Friday that Gov. Andrew Cuomo should step down amid allegations from six women that he engaged in sexual harassment.\r\nIn a joint statement, Senate Majority \u2026 [+1331 chars]"
      },
      {
         "source": {
            "id": "business-insider",
            "name": "Business Insider"
         },
         "author": "hrobertson@businessinsider.com (Harry Robertson)",
         "title": "Number of women trading crypto grows by 7 times so far in 2021 on Robinhood as interest in bitcoin booms",
         "description": "\"Our data shows that things are changing,\" Robinhood said in a blog post.",
         "url": "https://www.businessinsider.com/robinhood-women-trading-crypto-bitcoin-btc-ethereum-eth-2021-3",
         "urlToImage": "https://i.insider.com/604b476cfea127001886a5ea?width=1200&format=jpeg",
         "publishedAt": "2021-03-12T11:19:21Z",
         "content": "Move over, bitcoin bros. Cryptocurrencies are drawing in a rapidly growing number of female traders this year.\r\nRobinhood said on Thursday the number of women trading crypto on its platform has jumpe\u2026 [+1730 chars]"
      },
      {
         "source": {
            "id": "business-insider",
            "name": "Business Insider"
         },
         "author": "insider@insider.com (Isobel Asher Hamilton)",
         "title": "Russia claims a fire at a data center in France broke access to Google and YouTube. Google says that's not true.",
         "description": "The Google outage in Russia happened on the same day the state accidentally broke its own internet while trying to censor Twitter.",
         "url": "https://www.businessinsider.com/google-russia-internet-outage-fire-data-center-twitter-censorship-censor-2021-3",
         "urlToImage": "https://i.insider.com/604b3f33fea127001886a5d1?width=1200&format=jpeg",
         "publishedAt": "2021-03-12T11:14:37Z",
         "content": "On the same day Russia botched its attempt to censor Twitter, dozens of other websites, including Google and YouTube, went down. Russia is now trying to blame the damage on a fire in another country \u2026 [+1664 chars]"
      },
      {
         "source": {
            "id": "business-insider",
            "name": "Business Insider"
         },
         "author": "insider@insider.com (David Shepardson and Heekyong Yang)",
         "title": "LG plans to invest $4.5 billion in US battery production to meet growing electric-vehicle demand, including building at least 2 factories",
         "description": "LG Energy Solution's four-year nvestment in battery production, aimed to meet growing EV demand, would create 4,000 new jobs, a senior executive said.",
         "url": "https://www.businessinsider.com/lg-energy-solution-us-battery-production-electric-vehicles-investment-factories-2021-3",
         "urlToImage": "https://i.insider.com/604b4badfea127001886a5f8?width=1200&format=jpeg",
         "publishedAt": "2021-03-12T11:37:52Z",
         "content": "South Korea's LG Energy Solution, a division of LG Chem which manufactures batteries, plans to invest more than $4.5 billion in its US battery production business over the next four years, a senior e\u2026 [+1740 chars]"
      },
      {
         "source": {
            "id": "business-insider",
            "name": "Business Insider"
         },
         "author": "jberke@businessinsider.com (Jeremy Berke,Yeji Jesse Lee)",
         "title": "Insider Cannabis: A psychedelic research renaissance - layoffs at Acreage - Curaleaf's European ambitions",
         "description": "Welcome to Insider Cannabis, where we're bringing you an inside look at the deals, trends, and personalities driving the multibillion-dollar cannabis boom.",
         "url": "https://www.businessinsider.com/insider-cannabis-newsletter-march-12-2021-3",
         "urlToImage": "https://i.insider.com/604651f82db4af00117e416f?width=1200&format=jpeg",
         "publishedAt": "2021-03-12T17:48:19Z",
         "content": "Welcome to Insider Cannabis, our weekly newsletter where we're bringing you an inside look at the deals, trends, and personalities driving the multibillion-dollar global cannabis boom.\r\nSign up here \u2026 [+3896 chars]"
      },
      {
         "source": {
            "id": "business-insider",
            "name": "Business Insider"
         },
         "author": "insider@insider.com (Jake Lahut,Grace Panetta)",
         "title": "Cuomo reportedly tried to discredit a woman accusing him of sexual harassment by having his staff call her former coworkers",
         "description": "\"It's a scary thing to get a call like that,\" one NY lawmaker previously told Insider. A Cuomo accuser was also among the former employees called.",
         "url": "https://www.businessinsider.com/cuomo-staff-tried-to-discredit-1st-harassment-accuser-report-2021-3",
         "urlToImage": "https://i.insider.com/604b8f9bfea127001886a6f3?width=1200&format=jpeg",
         "publishedAt": "2021-03-12T17:39:37Z",
         "content": "Back in December when former Andrew Cuomo aide Lindsey Boylan came forward with allegations of sexual harassment by the governor, current staffers began working the phones to get dirt on Boylan and s\u2026 [+3098 chars]"
      },
      {
         "source": {
            "id": "business-insider",
            "name": "Business Insider"
         },
         "author": "Jake Lahut",
         "title": "Cuomo again refuses to step down, says lawmakers calling for his resignation are 'bowing to cancel culture'",
         "description": "Summary List PlacementNew York Gov. Andrew Cuomo once again refused to resign on Friday after more Democrats at the state and federal level called for his ouster.\n\"I did not do what has been alleged, period,\" Cuomo said on a conference call with reporters.\n\"P\u2026",
         "url": "https://www.businessinsider.com/andrew-cuomo-press-conference-refuse-resign-bowing-cancel-culture-2021-3",
         "urlToImage": "https://i.insider.com/604bb10710c8760018b92f9f?width=1200&format=jpeg",
         "publishedAt": "2021-03-12T18:29:49Z",
         "content": "New York Gov. Andrew Cuomo once again refused to resign on Friday after more Democrats at the state and federal level called for his ouster.\r\n\"I did not do what has been alleged, period,\" Cuomo said \u2026 [+1223 chars]"
      },
      {
         "source": {
            "id": "business-insider",
            "name": "Business Insider"
         },
         "author": "Aria Bendix",
         "title": "The new stimulus bill includes a groundbreaking basic-income policy \u2014 parents can receive up to $3,600 per child this year",
         "description": "Summary List PlacementPresident Joe Biden signed the $1.9 trillion COVID-19 stimulus bill into law on Thursday. Tucked into it is a $100 billion plan to offer most parents recurring monthly checks from July through December: $300 per child under age 6 and $25\u2026",
         "url": "https://www.businessinsider.com/child-allowance-payment-stimulus-bill-basic-income-2021-3",
         "urlToImage": "https://i.insider.com/6018294e6dfbe10018e010e4?width=1200&format=jpeg",
         "publishedAt": "2021-03-12T18:56:26Z",
         "content": "President Joe Biden signed the $1.9 trillion COVID-19 stimulus bill into law on Thursday. Tucked into it is a $100 billion plan to offer most parents recurring monthly checks from July through Decemb\u2026 [+4639 chars]"
      },
      {
         "source": {
            "id": "business-insider",
            "name": "Business Insider"
         },
         "author": "insider@insider.com (Abraham Andreu)",
         "title": "Why Spain doesn't have its own space agency",
         "description": "Minister Pedro Duque explained why Spain does not have a space agency, unlike neighboring countries such as Italy. Even so, there is an agency in charge of scientific research and the provision of technological services in Spain, the National Institute for Ae\u2026",
         "url": "https://www.businessinsider.com/spain-space-agency-esa-europe-orbit-moon-apollo-rover-mars-2021-3",
         "urlToImage": "https://www.businessinsider.com/public/assets/BI/US/og-image-logo-social.png",
         "publishedAt": "2021-03-12T14:05:40Z",
         "content": "This is an automated machine translation of an article published by Business Insider in a different language. Machine translations can generate errors or inaccuracies; we will continue the work to im\u2026 [+2905 chars]"
      },
      {
         "source": {
            "id": "business-insider",
            "name": "Business Insider"
         },
         "author": "insider@insider.com (Isabelle Lee)",
         "title": "Goldman Sachs creates SPAC team in Hong Kong amid surging Asian interest in blank-check companies",
         "description": "The strategic team was set up last year but was not made public, according to Reuters.",
         "url": "https://www.businessinsider.com/goldman-sachs-creates-spac-team-hong-kong-surging-asian-interest-2021-3",
         "urlToImage": "https://images2.markets.businessinsider.com/603d45da87d37600190d077e?format=jpeg",
         "publishedAt": "2021-03-12T13:57:13Z",
         "content": "Omar Marques/SOPA Images/LightRocket via Getty Images\r\nGoldman Sachs has created a SPAC team in Hong Kong dedicated to handling the surge in blank-check deals that have emerged in the Asian region.\r\n\u2026 [+1464 chars]"
      },
      {
         "source": {
            "id": "business-insider",
            "name": "Business Insider"
         },
         "author": "Emily Graffeo",
         "title": "Lordstown Motors plunges 23% after short-seller report says the EV SPAC has 'no revenue and no sellable product' (RIDE)",
         "description": "Summary List Placement<ul>\n<li>Shares of Lordstown Motors fell as much as 23% on Friday after Hindenburg Research revealed it has a short position in the electric-vehicle maker.\u00a0</li>\n<li>The research firm said Lordstown has misled investors and has \"no reven\u2026",
         "url": "https://www.businessinsider.com/lordstown-motors-stock-price-hindenburg-research-short-seller-electric-vehicle-2021-3",
         "urlToImage": "https://i.insider.com/604b8c4db197370019694a76?width=1200&format=jpeg",
         "publishedAt": "2021-03-12T16:31:46Z",
         "content": "Shares of Lordstown Motors tumbled as much as 23% on Friday after short-seller Hindenburg Research said the electric pickup truck maker has misled investors.\u00a0\u00a0\r\nThe research firm said it had taken a \u2026 [+986 chars]"
      },{
         "source": {
            "id": "the-washington-post",
            "name": "The Washington Post"
         },
         "author": "Karla Adam",
         "title": "Prince William says royals 'very much not a racist family'",
         "description": "William was attending a school opening when he was asked about his brother's interview.",
         "url": "https://www.washingtonpost.com/world/europe/prince-william-response-racism-britain/2021/03/11/c5de88ce-825d-11eb-be22-32d331d87530_story.html",
         "urlToImage": "https://www.washingtonpost.com/wp-apps/imrs.php?src=https://arc-anglerfish-washpost-prod-washpost.s3.amazonaws.com/public/5X6WJCECLUI6XHFGKTQYP3SJHE.jpg&w=1440",
         "publishedAt": "2021-03-11T12:03:10Z",
         "content": "Queen Elizabeth II saddened by Harry and Meghans descriptions of rejection, racism\r\nThe Duke and Duchess of Cambridge were attending a public event at a school in east London when a reporter asked if\u2026 [+1001 chars]"
      },
      {
         "source": {
            "id": "the-washington-post",
            "name": "The Washington Post"
         },
         "author": "Jennifer Rubin",
         "title": "What to listen for in Biden\u2019s prime-time speech",
         "description": "Biden needs to take account and look forward.",
         "url": "https://www.washingtonpost.com/opinions/2021/03/11/what-listen-bidens-primetime-speech/",
         "urlToImage": "https://www.washingtonpost.com/wp-apps/imrs.php?src=https://arc-anglerfish-washpost-prod-washpost.s3.amazonaws.com/public/27PZK3M3R5FNTCZ5HDG3EVEF5M.jpg&w=1440",
         "publishedAt": "2021-03-11T15:00:50Z",
         "content": "First, he should enjoy a victory lap, not for the sake of rubbing Republicans nose in his legislative victory, but to make clear that Democrats are delivering in a big way despite total Republican op\u2026 [+3451 chars]"
      },
      {
         "source": {
            "id": "the-washington-post",
            "name": "The Washington Post"
         },
         "author": "Ann Hornaday, A.H.",
         "title": "New movies to stream this week: \u2018The Inheritance,\u2019 \u2018Quo Vadis, Aida?\u2019 and more",
         "description": "Watch these new movies from home.",
         "url": "https://www.washingtonpost.com/goingoutguide/movies/march-12-new-streaming-movie-roundup/2021/03/09/6f09f308-7d12-11eb-b3d1-9e5aa3d5220c_story.html",
         "urlToImage": "https://www.washingtonpost.com/wp-apps/imrs.php?src=https://arc-anglerfish-washpost-prod-washpost.s3.amazonaws.com/public/HZUZ5TUBHMI6XHFGKTQYP3SJHE.jpg&w=1440",
         "publishedAt": "2021-03-11T15:00:00Z",
         "content": "HBO documentary about the 1978 MOVE standoff is a distressing look at the past and the present\r\nA ferocious, unrelenting sense of urgency drives Quo Vadis, Aida?, Jasmila Zbanics propulsive thriller \u2026 [+5235 chars]"
      },
      {
         "source": {
            "id": "the-washington-post",
            "name": "The Washington Post"
         },
         "author": "Reis Thebault, Tim Meko, Junne Alcantara",
         "title": "A year of covid-19: Timeline of the pandemic in America - The Washington Post",
         "description": "For most Americans, March 11 was the day the coronavirus crisis first became real. Fifty-two weeks later, millions have fallen ill and millions more have been vaccinated. More than 525,000 are dead. This timeline tells the story of a singular period in histor\u2026",
         "url": "https://www.washingtonpost.com/nation/interactive/2021/coronavirus-timeline/",
         "urlToImage": "https://www.washingtonpost.com/wp-apps/imrs.php?src=https://arc-anglerfish-washpost-prod-washpost.s3.amazonaws.com/public/VZDXDDCB5ZEYZP3X4FOIOINYWQ.jpg&w=1200",
         "publishedAt": "2021-03-11T14:18:05Z",
         "content": "Nyesha Montes De Oca, 38, paints the toenails of her mother, Irene Gonzalez, 66, at a Los Angeles mortuary on Jan. 13. \"Million-dollar Red,\" she says. \"Her favorite.\" (Philip Cheung for The Washingto\u2026 [+2887 chars]"
      },
      {
         "source": {
            "id": "the-washington-post",
            "name": "The Washington Post"
         },
         "author": "Craig Timberg",
         "title": "QAnon groups on Telegram seethe with covid denialism and vaccine misinformation",
         "description": "Conspiracy theories about covid and vaccines once ran rampant on the likes of Facebook, Twitter and YouTube. But months of purges of accounts that trafficked heavily in misinformation - especially after the baseless QAnon ideology helped fuel the Jan. 6 siege\u2026",
         "url": "https://www.washingtonpost.com/technology/2021/03/11/with-trump-gone-qanon-groups-focus-fury-attacking-covid-vaccines/",
         "urlToImage": "https://www.washingtonpost.com/wp-apps/imrs.php?src=https://arc-anglerfish-washpost-prod-washpost.s3.amazonaws.com/public/3BTY7OC3P4I6XKCJN6KCHJ277U.jpg&w=1440",
         "publishedAt": "2021-03-11T13:00:06Z",
         "content": "Such unhinged conspiracy theories once ran rampant on Facebook, Twitter and YouTube. But months of purging accounts that trafficked heavily in the baseless QAnon ideology especially after it helped f\u2026 [+12087 chars]"
      },
      {
         "source": {
            "id": "the-washington-post",
            "name": "The Washington Post"
         },
         "author": "Gary Trudeau",
         "title": "Doonesbury for Thursday, March 11, 2021",
         "description": "",
         "url": "http://wpcomics.washingtonpost.com/client/wpc/db/2021/03/11/",
         "urlToImage": null,
         "publishedAt": "2021-03-11T13:00:00Z",
         "content": null
      },
      {
         "source": {
            "id": "the-washington-post",
            "name": "The Washington Post"
         },
         "author": "Rick Noack",
         "title": "Denmark temporarily suspends AstraZeneca vaccine, even as European regulator maintains it is safe",
         "description": "The announcement followed concerns over potential side effects of the vaccine.",
         "url": "https://www.washingtonpost.com/world/denmark-temporarily-suspends-astrazeneca-vaccine-even-as-european-regulator-maintains-it-is-safe/2021/03/11/d48662e8-8267-11eb-be22-32d331d87530_story.html",
         "urlToImage": "https://www.washingtonpost.com/wp-apps/imrs.php?src=https://arc-anglerfish-washpost-prod-washpost.s3.amazonaws.com/public/H6MGCUUCNYI6XLBXIOB7O4E2XY.jpg&w=1440",
         "publishedAt": "2021-03-11T13:32:58Z",
         "content": "Danish authorities added that reports of a death in Denmark are also being investigated, without providing details.\r\nThere is good evidence that the vaccine is both safe and effective, said Soren Bro\u2026 [+2204 chars]"
      },
      {
         "source": {
            "id": "the-washington-post",
            "name": "The Washington Post"
         },
         "author": "Emily Yahr",
         "title": "Shrewd and sharp, empathetic and disarming: How Oprah interview went from must-see TV to cultural phenomenon...",
         "description": "Shrewd and sharp, empathetic and disarming: How Oprah interview went from must-see TV to cultural phenomenon...\r\n\n \n \n \n (First column, 12th story, link)\r\n\n \r\n\n \r\n\n \n Related stories:Prince William defends royal family against racism claims...\r\nBrother slaps \u2026",
         "url": "https://www.washingtonpost.com/arts-entertainment/2021/03/11/oprah-winfrey-interview-meghan-harry/",
         "urlToImage": "https://s.hdnux.com/photos/01/17/04/72/20729483/3/rawImage.jpg",
         "publishedAt": "2021-03-11T15:49:37Z",
         "content": "A telephone ringing at 4:30 in the morning is rarely good news, so television executive Ted Harbert will never forget the day in 1993 that he was awakened at home in Los Angeles by a call from his bo\u2026 [+7757 chars]"
      },
      {
         "source": {
            "id": "the-washington-post",
            "name": "The Washington Post"
         },
         "author": "David Streit",
         "title": "D.C.-area forecast: Record-challenging warmth today before a cooldown this weekend",
         "description": "Well into the 70s today, but only 40s for highs on Monday.",
         "url": "https://www.washingtonpost.com/weather/2021/03/11/dc-area-forecast-record-challenging-warmth-today-before-cool-down-this-weekend/",
         "urlToImage": "https://www.washingtonpost.com/wp-apps/imrs.php?src=https://arc-anglerfish-washpost-prod-washpost.s3.amazonaws.com/public/AZSILVEBCMI6XPRCGLJTDWDVGA.jpg&w=1440",
         "publishedAt": "2021-03-11T10:00:47Z",
         "content": "Get our daily forecasts on your Amazon Alexa device.\r\nToday (Thursday): Clouds are possible across the area at sunrise but should disperse fairly quickly in the morning. This allows temperatures to c\u2026 [+2014 chars]"
      },
      {
         "source": {
            "id": "the-washington-post",
            "name": "The Washington Post"
         },
         "author": "David Ebner, Vladimir Enrique Medenica",
         "title": "If you want to know what Americans think about bombing Iran, find out what they think about race",
         "description": "That matters, because when political leaders shape foreign policy, they keep public opinion in mind.",
         "url": "https://www.washingtonpost.com/politics/2021/03/11/if-you-want-know-what-americans-think-about-bombing-iran-find-out-what-they-think-about-race/",
         "urlToImage": "https://www.washingtonpost.com/wp-apps/imrs.php?src=https://arc-anglerfish-washpost-prod-washpost.s3.amazonaws.com/public/ANV2JVTFJQI6VCUOLRJTNMZHMA.jpg&w=1440",
         "publishedAt": "2021-03-11T11:00:25Z",
         "content": "This action, while a first for the Biden administration, is part of a larger pattern of military confrontation between the United States and Iran since the Trump administration decided to leave the J\u2026 [+5410 chars]"
      },
      {
         "source": {
            "id": "the-washington-post",
            "name": "The Washington Post"
         },
         "author": "Aaron Blake",
         "title": "How the coronavirus has touched most Americans personally, over time",
         "description": "A poll from the Economist and YouGov this week showed that fully 62 percent of Americans personally know someone who has been diagnosed.",
         "url": "https://www.washingtonpost.com/politics/2021/03/11/how-coronavirus-has-touched-most-americans-personally-over-time/",
         "urlToImage": "https://www.washingtonpost.com/wp-apps/imrs.php?src=https://d1i4t8bqe7zgj6.cloudfront.net/03-11-2021/t_6744f20c5f784f48aae23c88ccbffc9d_name_7d1cbd3a_829f_11eb_be22_32d331d87530_scaled.jpg&w=1440",
         "publishedAt": "2021-03-11T21:11:13Z",
         "content": "That number means that nearly 1 in 600 Americans have died. Whats more, nearly 9 percent of the population has tested positive so far.\r\nBut those numbers dont show the full picture of how the virus h\u2026 [+2211 chars]"
      },
      {
         "source": {
            "id": "the-washington-post",
            "name": "The Washington Post"
         },
         "author": "Amy Gardner",
         "title": "Recording reveals details of Trump call to Georgia\u2019s chief elections investigator",
         "description": "In the Dec. 23 conversation, the then-president urged the chief investigator for Secretary of State Brad Raffensperger to do \u201cwhatever you can do\u201d to uncover wrongdoing in the election.",
         "url": "https://www.washingtonpost.com/politics/trump-call-georgia-investigator/2021/03/11/c532ea2e-827a-11eb-ac37-4383f7709abe_story.html",
         "urlToImage": "https://www.washingtonpost.com/wp-apps/imrs.php?src=https://arc-anglerfish-washpost-prod-washpost.s3.amazonaws.com/public/HVNCAVDHE4I6XOVYOB7YO2OXQU.jpg&w=1440",
         "publishedAt": "2021-03-11T20:15:32Z",
         "content": "The people of Georgia are so angry at what happened to me, Trump told Frances Watson, the chief investigator for Georgia Secretary of State Brad Raffensperger, according to the recording. They know I\u2026 [+5287 chars]"
      },
      {
         "source": {
            "id": "the-washington-post",
            "name": "The Washington Post"
         },
         "author": "Aaron Blake, Eugene Scott, JM Rieger, Natalie Jennings, Peter Stevenson",
         "title": "Politics with The Fix Live Chat: March 18",
         "description": "Join Washington Post reporters every Thursday at 12 pm ET for a discussion on the latest in politics.",
         "url": "https://www.washingtonpost.com/politics/2021/03/11/live-chat-politics-the-fix/",
         "urlToImage": "https://www.washingtonpost.com/wp-apps/imrs.php?src=https://arc-anglerfish-washpost-prod-washpost.s3.amazonaws.com/public/HI3TD4LP3VEU7MEPVJNGJKS25Q.jpg&w=1440",
         "publishedAt": "2021-03-11T18:20:33Z",
         "content": null
      },
      {
         "source": {
            "id": "the-washington-post",
            "name": "The Washington Post"
         },
         "author": "Jennifer Rubin",
         "title": "Nancy Pelosi is a force of nature",
         "description": "The House speaker was in fine form on Thursday after passage of the covid-19 relief bill.",
         "url": "https://www.washingtonpost.com/opinions/2021/03/11/nancy-pelosi-is-force-nature/",
         "urlToImage": "https://www.washingtonpost.com/wp-apps/imrs.php?src=https://arc-anglerfish-washpost-prod-washpost.s3.amazonaws.com/public/DTTAQGUCREI6XPRCGLJTDWDVGA.jpg&w=1440",
         "publishedAt": "2021-03-11T18:05:49Z",
         "content": "Pelosi was cheerfully withering in her critique of Republicans, who unanimously opposed the rescue plan. Unfortunately, Republicans, as I say, vote no and take the dough, she wisecracked. Perhaps in \u2026 [+2826 chars]"
      },
      {
         "source": {
            "id": "the-washington-post",
            "name": "The Washington Post"
         },
         "author": "Missy Ryan, Alex Horton",
         "title": "Military leaders reject Tucker Carlson\u2019s assertion that efforts to retain female troops are a \u2018mockery\u2019 - The Washington Post",
         "description": "<ol><li>Military leaders reject Tucker Carlson\u2019s assertion that efforts to retain female troops are a \u2018mockery\u2019\u00a0\u00a0The Washington Post\r\n</li><li>Pentagon and senior members of military call out Tucker Carlson for mocking women serving in armed forces: His words\u2026",
         "url": "https://www.washingtonpost.com/national-security/tucker-carlson-women-military-fox/2021/03/11/c1d9e3c6-826d-11eb-bb5a-ad9a91faa4ef_story.html",
         "urlToImage": "https://www.washingtonpost.com/wp-apps/imrs.php?src=https://arc-anglerfish-washpost-prod-washpost.s3.amazonaws.com/public/YX7GJGUCPQI6XAO3WAXQHGHUTI.jpg&w=1440",
         "publishedAt": "2021-03-11T16:55:00Z",
         "content": "While Chinas military becomes more masculine as it has assembled the worlds largest navy, our military needs to become as Joe Biden says more feminine, whatever feminine means anymore, Carlson said, \u2026 [+4190 chars]"
      },
      {
         "source": {
            "id": "the-washington-post",
            "name": "The Washington Post"
         },
         "author": "Jason Samenow",
         "title": "D.C.-area temperatures charge to record highs amid spiking tree pollen",
         "description": "Cherry blossoms hit first stage in bloom cycle",
         "url": "https://www.washingtonpost.com/weather/2021/03/11/dc-record-highs-march11/",
         "urlToImage": "https://www.washingtonpost.com/wp-apps/imrs.php?src=https://arc-anglerfish-washpost-prod-washpost.s3.amazonaws.com/public/4LL32RIVGJFOTHW4EXX7GPY4PE.PNG&w=1440",
         "publishedAt": "2021-03-11T20:06:53Z",
         "content": "Through 3 p.m., temperatures at all three D.C.-area airports had seen temperatures reach the upper 70s, topping previous records at Dulles and in Baltimore:\r\n<ul><li>Reagan National had hit at least \u2026 [+2682 chars]"
      },
      {
         "source": {
            "id": "the-washington-post",
            "name": "The Washington Post"
         },
         "author": "Ian Livingston",
         "title": "PM Update: Record warmth of today tapers somewhat Friday",
         "description": "Temperatures closed in on 80 this afternoon. Cooler, with a chance of a few showers tomorrow.",
         "url": "https://www.washingtonpost.com/weather/2021/03/11/pm-update-record-warmth-today-tapers-somewhat-friday/",
         "urlToImage": "https://www.washingtonpost.com/wp-apps/imrs.php?src=https://arc-anglerfish-washpost-prod-washpost.s3.amazonaws.com/public/EZ5WOSR75NCRZD545AZE6T6FV4.jpg&w=1440",
         "publishedAt": "2021-03-11T21:45:58Z",
         "content": "Listen to our daily D.C. forecasts: Apple Podcasts | Amazon Echo | More options\r\nThrough Tonight: Clouds increase as a cold front approaches, and a sprinkle or quick shower is possible in the hours b\u2026 [+1119 chars]"
      },
      {
         "source": {
            "id": "the-washington-post",
            "name": "The Washington Post"
         },
         "author": "Sam Fortier",
         "title": "New GM Martin Mayhew once again returns to Washington with unfinished business",
         "description": "Martin Mayhew, a key piece of Washington's revamped front office, returned to Washington to finish his law degree after his playing days were over.",
         "url": "https://www.washingtonpost.com/sports/2021/03/11/martin-mayhew-gm-washington-football-team/",
         "urlToImage": "https://www.washingtonpost.com/wp-apps/imrs.php?src=https://arc-anglerfish-washpost-prod-washpost.s3.amazonaws.com/public/JCJS6ALAKFBOVA3RJGXWLVOHLI.jpg&w=1440",
         "publishedAt": "2021-03-11T16:38:11Z",
         "content": "But that story misses the bigger picture. In 93, Mayhew left for Tampa Bay in free agency and paused his studies. Three years later, he retired, returned to Washington and, at 31, restarted law schoo\u2026 [+12174 chars]"
      },
      {
         "source": {
            "id": "the-washington-post",
            "name": "The Washington Post"
         },
         "author": "Seung Min Kim",
         "title": "Next Biden agenda items on immigration and infrastructure already running into trouble",
         "description": "Fresh off a major victory on a $1.9 trillion coronavirus relief package, the president and his Democratic allies face resistance in their own ranks to tackling other priorities without some Republican support.",
         "url": "https://www.washingtonpost.com/politics/biden-agenda-next/2021/03/11/fd2b67b4-8296-11eb-ac37-4383f7709abe_story.html",
         "urlToImage": "https://www.washingtonpost.com/wp-apps/imrs.php?src=https://arc-anglerfish-washpost-prod-washpost.s3.amazonaws.com/public/WJCDIUUB5MI6XPRCGLJTDWDVGA.jpg&w=1440",
         "publishedAt": "2021-03-12T00:58:18Z",
         "content": "And thats before Democrats begin grappling with the hurdle that is the Senate filibuster.\r\nThe complicated dynamics among Democrats on Capitol Hill show that getting the type of unity the party attai\u2026 [+8622 chars]"
      },
      {
         "source": {
            "id": "the-washington-post",
            "name": "The Washington Post"
         },
         "author": "Aaron Blake",
         "title": "3 takeaways from Biden\u2019s first primetime address to the nation",
         "description": "It came on the anniversary of the coronavirus outbreak being labeled a pandemic and on the day he signed a $1.9 trillion relief package \u2014 the first major piece of his agenda to pass through Congress.",
         "url": "https://www.washingtonpost.com/politics/2021/03/11/takweaways-biden-address/",
         "urlToImage": "https://www.washingtonpost.com/wp-apps/imrs.php?src=https://d1i4t8bqe7zgj6.cloudfront.net/03-12-2021/t_5977a6813e26458991ca645c3017254e_name_bidnen_scaled.jpg&w=1440",
         "publishedAt": "2021-03-12T02:09:32Z",
         "content": "Its been just under a year since former president Donald Trump set an ambitious goal for moving beyond the coronavirus, aiming to have things fully open again by an upcoming holiday: Easter. That goa\u2026 [+4445 chars]"
      }
   

]